CHANGES.txt
README.txt
setup.py
collective/__init__.py
collective.collage.feedfeeder.egg-info/PKG-INFO
collective.collage.feedfeeder.egg-info/SOURCES.txt
collective.collage.feedfeeder.egg-info/dependency_links.txt
collective.collage.feedfeeder.egg-info/namespace_packages.txt
collective.collage.feedfeeder.egg-info/not-zip-safe
collective.collage.feedfeeder.egg-info/requires.txt
collective.collage.feedfeeder.egg-info/top_level.txt
collective/collage/__init__.py
collective/collage/feedfeeder/__init__.py
collective/collage/feedfeeder/browser.py
collective/collage/feedfeeder/configure.zcml
collective/collage/feedfeeder/templates/feedfolder_standard.pt