Metadata-Version: 1.0
Name: collective.collage.feedfeeder
Version: 1.0
Summary: Collage add-on that allows displaying RSS-feeds.
Home-page: http://www.plone.org/products/collective.collage.feedfeeder
Author: Malthe Borch
Author-email: mborch@gmail.com
License: GPL
Keywords: collage plone rss feedfeeder
Platform: UNKNOWN
Classifier: Programming Language :: Python
Classifier: Framework :: Plone
Classifier: License :: OSI Approved :: GNU General Public License (GPL)
Classifier: Development Status :: 5 - Production/Stable
